pymeos/__init__.py
pymeos/factory.py
pymeos/meos_init.py
pymeos/aggregators/__init__.py
pymeos/aggregators/aggregator.py
pymeos/aggregators/bool_aggregators.py
pymeos/aggregators/general_aggregators.py
pymeos/aggregators/number_aggregators.py
pymeos/aggregators/point_aggregators.py
pymeos/aggregators/text_aggregators.py
pymeos/aggregators/time_aggregators.py
pymeos/boxes/__init__.py
pymeos/boxes/box.py
pymeos/boxes/stbox.py
pymeos/boxes/tbox.py
pymeos/collections/__init__.py
pymeos/collections/base/__init__.py
pymeos/collections/base/collection.py
pymeos/collections/base/set.py
pymeos/collections/base/span.py
pymeos/collections/base/spanset.py
pymeos/collections/geo/__init__.py
pymeos/collections/geo/geoset.py
pymeos/collections/number/__init__.py
pymeos/collections/number/floatset.py
pymeos/collections/number/floatspan.py
pymeos/collections/number/floatspanset.py
pymeos/collections/number/intset.py
pymeos/collections/number/intspan.py
pymeos/collections/number/intspanset.py
pymeos/collections/text/__init__.py
pymeos/collections/text/textset.py
pymeos/collections/time/__init__.py
pymeos/collections/time/dateset.py
pymeos/collections/time/datespan.py
pymeos/collections/time/datespanset.py
pymeos/collections/time/time.py
pymeos/collections/time/timecollection.py
pymeos/collections/time/tstzset.py
pymeos/collections/time/tstzspan.py
pymeos/collections/time/tstzspanset.py
pymeos/db/__init__.py
pymeos/db/asyncpg.py
pymeos/db/db_objects.py
pymeos/db/psycopg.py
pymeos/db/psycopg2.py
pymeos/main/__init__.py
pymeos/main/tbool.py
pymeos/main/tfloat.py
pymeos/main/tint.py
pymeos/main/tnumber.py
pymeos/main/tpoint.py
pymeos/main/ttext.py
pymeos/mixins/__init__.py
pymeos/mixins/comparison.py
pymeos/mixins/simplify.py
pymeos/mixins/temporal_comparison.py
pymeos/plotters/__init__.py
pymeos/plotters/box_plotter.py
pymeos/plotters/point_sequence_plotter.py
pymeos/plotters/point_sequenceset_plotter.py
pymeos/plotters/range_plotter.py
pymeos/plotters/sequence_plotter.py
pymeos-1.2.1.dist-info/LICENSE
pymeos-1.2.1.dist-info/METADATA
pymeos-1.2.1.dist-info/WHEEL
pymeos-1.2.1.dist-info/top_level.txt
pymeos-1.2.1.dist-info/RECORD
