Metadata-Version: 2.1
Name: pymeos
Version: 1.2.1
Summary: Python wrapper for the MEOS C Library.
Author-email: Victor Divi <vdiviloper@gmail.com>, Zhicheng Luo <zhicheng.luo@ulb.be>, Krishna Chaitanya Bommakanti <bkchaitan94@gmail.com>
License: PostgreSQL License
Project-URL: Homepage, https://github.com/MobilityDB/PyMEOS/pymeos
Project-URL: Bug Tracker, https://github.com/MobilityDB/PyMEOS/issues
Project-URL: Changelog, https://github.com/MobilityDB/PyMEOS/blob/master/pymeos/CHANGELOG.md
Classifier: License :: OSI Approved :: PostgreSQL License
Classifier: Development Status :: 4 - Beta
Classifier: Intended Audience :: Developers
Classifier: Intended Audience :: Science/Research
Classifier: Programming Language :: C
Classifier: Programming Language :: Python
Classifier: Programming Language :: Python :: 3
Classifier: Programming Language :: Python :: 3.8
Classifier: Programming Language :: Python :: 3.9
Classifier: Programming Language :: Python :: 3.10
Classifier: Programming Language :: Python :: 3.11
Classifier: Programming Language :: Python :: 3 :: Only
Classifier: Programming Language :: Python :: Implementation :: CPython
Classifier: Operating System :: POSIX
Classifier: Operating System :: Unix
Requires-Python: >=3.8
License-File: LICENSE
Requires-Dist: pymeos-cffi <2,>=1.2.0
Requires-Dist: python-dateutil
Requires-Dist: shapely >=2.0.0
Provides-Extra: dba
Requires-Dist: asyncpg ; extra == 'dba'
Provides-Extra: dbp
Requires-Dist: psycopg ; extra == 'dbp'
Provides-Extra: dbp2
Requires-Dist: psycopg2 ; extra == 'dbp2'
Provides-Extra: pandas
Requires-Dist: geopandas ; extra == 'pandas'
Provides-Extra: plot
Requires-Dist: matplotlib ; extra == 'plot'
